p4/__init__.py
p4/config/__init__.py
p4/config/v1/__init__.py
p4/config/v1/p4info_pb2.py
p4/config/v1/p4info_pb2_grpc.py
p4/config/v1/p4types_pb2.py
p4/config/v1/p4types_pb2_grpc.py
p4/v1/__init__.py
p4/v1/p4data_pb2.py
p4/v1/p4data_pb2_grpc.py
p4/v1/p4runtime_pb2.py
p4/v1/p4runtime_pb2_grpc.py
p4runtime-1.4.1.dist-info/LICENSE
p4runtime-1.4.1.dist-info/METADATA
p4runtime-1.4.1.dist-info/WHEEL
p4runtime-1.4.1.dist-info/top_level.txt
p4runtime-1.4.1.dist-info/RECORD
