Metadata-Version: 2.1
Name: p4runtime
Version: 1.4.1
Summary: Python bindings for P4Runtime protocol
Home-page: https://github.com/p4lang/p4runtime
Author: P4 API Working Group
Author-email: p4-api@lists.p4.org
License: Apache-2.0
Classifier: License :: OSI Approved :: Apache Software License
Classifier: Programming Language :: Python
Classifier: Programming Language :: Python :: 3
Requires-Python: >=3.6
License-File: LICENSE
Requires-Dist: protobuf>=3.6.1
Requires-Dist: grpcio>=1.17.2
Requires-Dist: googleapis-common-protos>=1.52
